azureml/__init__.py
azureml/accel/__init__.py
azureml/accel/_accel_container_image.py
azureml/accel/_accel_inference_config.py
azureml/accel/_accel_onnx_converter.py
azureml/accel/_client.py
azureml/accel/_version.py
azureml/accel/_data/accel_container_payload_template.json
azureml/accel/_external/__init__.py
azureml/accel/_external/ssdvgg_utils.py
azureml/accel/_external/tensorflow/LICENSE
azureml/accel/_external/tensorflow/__init__.py
azureml/accel/_external/tensorflow/graph_util_impl.py
azureml/accel/_external/tensorflow_serving/__init__.py
azureml/accel/_external/tensorflow_serving/apis/__init__.py
azureml/accel/_external/tensorflow_serving/apis/classification_pb2.py
azureml/accel/_external/tensorflow_serving/apis/get_model_metadata_pb2.py
azureml/accel/_external/tensorflow_serving/apis/inference_pb2.py
azureml/accel/_external/tensorflow_serving/apis/input_pb2.py
azureml/accel/_external/tensorflow_serving/apis/model_pb2.py
azureml/accel/_external/tensorflow_serving/apis/predict_pb2.py
azureml/accel/_external/tensorflow_serving/apis/prediction_service_pb2.py
azureml/accel/_external/tensorflow_serving/apis/prediction_service_pb2_grpc.py
azureml/accel/_external/tensorflow_serving/apis/regression_pb2.py
azureml/accel/models/__init__.py
azureml/accel/models/_densenet121.py
azureml/accel/models/_resnet152.py
azureml/accel/models/_resnet50.py
azureml/accel/models/_ssdvgg.py
azureml/accel/models/_vgg16.py
azureml/accel/models/accel_model.py
azureml/accel/models/doesnotexisterror.py
azureml/accel/models/utils.py
azureml_accel_models-1.60.0.dist-info/licenses/LICENSE.txt
azureml_accel_models-1.60.0.dist-info/METADATA
azureml_accel_models-1.60.0.dist-info/WHEEL
azureml_accel_models-1.60.0.dist-info/top_level.txt
azureml_accel_models-1.60.0.dist-info/RECORD
