Metadata-Version: 2.4
Name: azureml-accel-models
Version: 1.60.0
Summary: Used to create and train a model using various deep neural networks (DNNs).
Home-page: https://docs.microsoft.com/python/api/overview/azure/ml/?view=azure-ml-py
Author: Microsoft Corp
License: https://aka.ms/azureml-sdk-license
Classifier: Development Status :: 3 - Alpha
Classifier: Intended Audience :: Developers
Classifier: Intended Audience :: Science/Research
Classifier: License :: Other/Proprietary License
Classifier: Programming Language :: Python :: 3
Classifier: Programming Language :: Python :: 3.7
Classifier: Programming Language :: Python :: 3.8
Classifier: Programming Language :: Python :: 3.9
Classifier: Programming Language :: Python :: 3.10
Classifier: Programming Language :: Python :: 3.11
Classifier: Topic :: Scientific/Engineering :: Artificial Intelligence
Classifier: Operating System :: Microsoft :: Windows
Classifier: Operating System :: MacOS
Classifier: Operating System :: POSIX :: Linux
Requires-Python: >=3.7,<4.0
License-File: LICENSE.txt
Requires-Dist: grpcio>=1.0
Requires-Dist: azureml-core~=1.60.0
Provides-Extra: cpu
Requires-Dist: tensorflow<3.0.0,>=1.14.0; extra == "cpu"
Provides-Extra: gpu
Requires-Dist: tensorflow-gpu<3.0.0,>=1.14.0; extra == "gpu"
Dynamic: author
Dynamic: classifier
Dynamic: description
Dynamic: description-content-type
Dynamic: home-page
Dynamic: license
Dynamic: license-file
Dynamic: provides-extra
Dynamic: requires-dist
Dynamic: requires-python
Dynamic: summary
